cggnn/__init__.py
cggnn/importance.py
cggnn/run.py
cggnn/scripts/separability.py
cggnn/scripts/train.py
cggnn/separability.py
cggnn/train.py
cggnn/util/__init__.py
cggnn/util/constants.py
cggnn/util/interpretability/__init__.py
cggnn/util/interpretability/base_explainer.py
cggnn/util/interpretability/grad_cam.py
cggnn/util/interpretability/graph_pruning_explainer.py
cggnn/util/interpretability/lrp_gnn_explainer.py
cggnn/util/ml/__init__.py
cggnn/util/ml/base_model.py
cggnn/util/ml/cell_graph_model.py
cggnn/util/ml/layers/__init__.py
cggnn/util/ml/layers/constants.py
cggnn/util/ml/layers/dense_gin_layer.py
cggnn/util/ml/layers/gin_layer.py
cggnn/util/ml/layers/mlp.py
cggnn/util/ml/layers/multi_layer_gnn.py
cggnn/util/ml/layers/pna_layer.py
cggnn/util/pipeline.py
cggnn/util/util.py
cg_gnn-0.3.2.dist-info/LICENSE
cg_gnn-0.3.2.dist-info/METADATA
cg_gnn-0.3.2.dist-info/WHEEL
cg_gnn-0.3.2.dist-info/entry_points.txt
cg_gnn-0.3.2.dist-info/RECORD
