Metadata-Version: 2.1
Name: cg-gnn
Version: 0.3.2
Summary: Train a graph neural network on cell graphs.
Home-page: https://github.com/nadeemlab/cg-gnn
License: AGPL-3.0-or-later
Keywords: gnn,pathology,omics,single-cell,graph,network,deep-learning,machine-learning,cancer,predictive-modeling,predictive-medicine,precision-medicine,precision-oncology,precision-pathology,precision-health,precision-healthcare
Author: Carlin Liao
Author-email: liaoc2@mskcc.org
Requires-Python: >=3.10,<4.0
Classifier: License :: OSI Approved :: GNU Affero General Public License v3 or later (AGPLv3+)
Classifier: Programming Language :: Python :: 3
Classifier: Programming Language :: Python :: 3.10
Classifier: Programming Language :: Python :: 3.11
Classifier: Programming Language :: Python :: 3.12
Requires-Dist: h5py
Requires-Dist: matplotlib
Requires-Dist: numpy
Requires-Dist: pandas
Requires-Dist: scikit-learn
Requires-Dist: scipy
Requires-Dist: tables
Requires-Dist: tqdm
Project-URL: Repository, https://github.com/nadeemlab/cg-gnn
